cen_detect_hor/__about__.py
cen_detect_hor/__init__.py
cen_detect_hor/assertions.py
cen_detect_hor/clustering_to_phylogeny.py
cen_detect_hor/compare_phylogenies.py
cen_detect_hor/distance.py
cen_detect_hor/featureUtils.py
cen_detect_hor/filter_phylogeny.py
cen_detect_hor/hor.py
cen_detect_hor/hor_coherence.py
cen_detect_hor/hor_tree.py
cen_detect_hor/loops.py
cen_detect_hor/matrix_utils.py
cen_detect_hor/mixed_direction_hors.py
cen_detect_hor/parallel_distance.py
cen_detect_hor/phylogeny_sorting.py
cen_detect_hor/phylogeny_to_levels.py
cen_detect_hor/showHOR.py
cen_detect_hor/treeFromClusters.py
cen_detect_hor-0.0.3.dist-info/METADATA
cen_detect_hor-0.0.3.dist-info/WHEEL
cen_detect_hor-0.0.3.dist-info/licenses/LICENSE
cen_detect_hor-0.0.3.dist-info/RECORD
